{
  "id": "b2c.cbe.post.api-cbebirr-b2c-transfer.cbe",
  "title": "C2B > B2C > CBE > CBE",
  "method": "POST",
  "path": "/api/Cbebirr/b2c/transfer",
  "provider": "cbe",
  "flow": "b2c",
  "headers": [
    "x-arifpay-key"
  ],
  "body": {
    "templateId": null,
    "required": [
      "sessionId",
      "phoneNumber"
    ],
    "example": {
      "sessionId": "AC2F8BF0D3F7",
      "phoneNumber": "251954926213"
    }
  },
  "tags": [
    "c2b",
    "b2c",
    "cbe",
    "post",
    "api",
    "cbebirr",
    "transfer",
    "sessionid",
    "phonenumber"
  ]
}
